themachinethatgoesping/.dylibs/libomp.dylib
themachinethatgoesping/__init__.py
themachinethatgoesping/algorithms/__init__.py
themachinethatgoesping/algorithms_nanopy.cpython-311-darwin.so
themachinethatgoesping/echosounders/__init__.py
themachinethatgoesping/echosounders/evaluate/evaluate_ping_features.py
themachinethatgoesping/echosounders/index_functions/__init__.py
themachinethatgoesping/echosounders/index_functions/find_files.py
themachinethatgoesping/echosounders/index_functions/get_index_paths.py
themachinethatgoesping/echosounders/index_functions/index_file_functions.py
themachinethatgoesping/echosounders_nanopy.cpython-311-darwin.so
themachinethatgoesping/gridding/__init__.py
themachinethatgoesping/gridding/echogrid.py
themachinethatgoesping/gridding/forwardgridderlegacy.py
themachinethatgoesping/gridding/forwardgridderlegacynew.py
themachinethatgoesping/gridding/functions/__init__.py
themachinethatgoesping/gridding/functions/gridfunctions.py
themachinethatgoesping/gridding/functions/helperfunctions.py
themachinethatgoesping/navigation/__init__.py
themachinethatgoesping/navigation_nanopy.cpython-311-darwin.so
themachinethatgoesping/pingprocessing/__init__.py
themachinethatgoesping/pingprocessing/core/__init__.py
themachinethatgoesping/pingprocessing/core/asserts.py
themachinethatgoesping/pingprocessing/core/helper.py
themachinethatgoesping/pingprocessing/core/progress.py
themachinethatgoesping/pingprocessing/filter_pings/__init__.py
themachinethatgoesping/pingprocessing/filter_pings/by_features.py
themachinethatgoesping/pingprocessing/filter_pings/by_files.py
themachinethatgoesping/pingprocessing/filter_pings/by_region.py
themachinethatgoesping/pingprocessing/filter_pings/by_time.py
themachinethatgoesping/pingprocessing/filter_pings/by_time_list.py
themachinethatgoesping/pingprocessing/group_pings/__init__.py
themachinethatgoesping/pingprocessing/group_pings/dual_head.py
themachinethatgoesping/pingprocessing/overview/__init__.py
themachinethatgoesping-0.32.0.dist-info/LICENSE
themachinethatgoesping-0.32.0.dist-info/METADATA
themachinethatgoesping-0.32.0.dist-info/WHEEL
themachinethatgoesping-0.32.0.dist-info/RECORD
