Metadata-Version: 2.1
Name: themachinethatgoesping
Version: 0.32.0
Summary: Enable advanced processing for multibeam and singlebeam echosounder data.THIS PROJECT IS IN DEVELOPMENT.
Author-Email: Peter Urban <peter.urban@ugent.be>
License: Mozilla Public License Version 2.0
Classifier: Development Status :: 1 - Planning
Classifier: Programming Language :: Python
Project-URL: homepage, https://github.com/themachinethatgoesping
Project-URL: repository, https://github.com/themachinethatgoesping
Project-URL: documentation, https://themachinethatgoesping.readthedocs.io/en/latest/
Requires-Python: <3.15,>=3.11
Requires-Dist: numba
Requires-Dist: matplotlib
Requires-Dist: numpy>=1.26.0
Requires-Dist: tqdm
Requires-Dist: rasterio>=1.3.10
Requires-Dist: ipywidgets
Requires-Dist: pytimeparse2>=1.7.1
Requires-Dist: pandas>=2.1.0
Requires-Dist: pyarrow
Requires-Dist: scipy
Requires-Dist: pyqtgraph
Requires-Dist: jupyter-rfb
Requires-Dist: pyside6
Provides-Extra: test
Requires-Dist: jupyter; extra == "test"
